<ZT2Strings>
<entityname>
   <!--animal names-->
      <AmphiStiumpar>Pre-lenguado</AmphiStiumpar>
      <AmphiStiumpar_stt>Pre-lenguado</AmphiStiumpar_stt>
      <AmphiStiumpar_lower>El Pre-lenguado</AmphiStiumpar_lower>
      <AmphiStiumpar_ltt>
         <color r="255" g="248" b="178">
            <b>Pre-lenguado</b>
         </color>
         <br/>
         Haga clic y seleccione el Pre-lenguado
      </AmphiStiumpar_ltt>
      <!--egg names-->
      <AmphiStiumpar_Egg>Pre-lenguado</AmphiStiumpar_Egg>
      <AmphiStiumpar_Egg_stt>Pre-lenguado</AmphiStiumpar_Egg_stt>
      <AmphiStiumpar_Egg_lower>het Pre-lenguado</AmphiStiumpar_Egg_lower>
      <AmphiStiumpar_Egg_ltt>
         <color r="255" g="248" b="178">
            <b>Pre-lenguado</b>
         </color>
         <br/>Klik op dit icoon om het Pre-lenguado Ei te selecteren. Beweeg je muis en klik om de Pre-lenguado Ei te plaatsen.
      </AmphiStiumpar_Egg_ltt>
</entityname>
<zoopedia_amphistiumpar>
 <entry>Pre-lenguado</entry>
 <text>
  <cell pady="0" width="1000"/>
  <p/>
  <cell width="260"/>
  <cell width="640" height="320" bgimg="ui/zoopedia/topCellBg.dds">
   <cell width="600" padx="20" pady="20">
   
               <cell width="284">
						 <cell width="96" bgimg="ui/zoopedia/littleBox-128.tga">
						  <img src="entities/units/animals/AmphiStiumpar/AmphiStiumpar_Adult_F_icon.dds" sx="0" sy="0" sw="64" sh="64" height="96" width="96"/>
						 </cell>
						 <cell width="16">
						  <img src="ui/zoopedia/icon_male.dds" sx="0" sy="0" sw="64" sh="64" width="16" height="16"/>
						 </cell>
						 <cell width="16">
						  <img src="ui/zoopedia/icon_female.dds" sx="0" sy="0" sw="64" sh="64" width="16" height="16"/>
						 </cell>
						 <cell width="156"/>
                  <br/>   
                  <cell width="32" pady="0">               
                     <img src="ui/zoopedia/extinct.dds" sx="0" sy="0" sw="64" sh="64" width="32" height="32"/>
                  </cell>                 
                  <cell width="224" padx="10" pady="0">
                     <color r="255" g="255" b="255">
                      Status:
                     <br/>
                        <color r="0" g="255" b="0">
                      Extinto
                        </color>
                     </color>                  
                  </cell>
               </cell>   
   
    <cell width="128">
     <color r="255" g="255" b="255">Arrecife<br/></color>
     <img src="ui/icon_biomes/icon_reef.dds" sx="0" sy="0" sw="128" sh="128" width="96" height="96"/>
    </cell>
    <cell width="128">
     <color r="255" g="255" b="255">Monte Bolca<br/></color> 
     <img src="ui/icon_maplocations/pelagic_warm_oceans_worldwide.dds" sx="0" sy="0" sw="256" sh="256" width="96" height="96"/>
    </cell>
    <br/>
    <cell width="284" pady="10">
     <color r="255" g="255" b="255">Clase: Peces con aletas radiadas <i>(Actinopterygii)</i><br/>Orden: Lenguados <i>(Pleuronectiformes)</i><br/>Familia: Pre-lenguados <i>(Amphistiumidae)</i><br/>Gemero: Amphistium <i>paradoxum</i>
     </color>
    </cell>
    <cell width="256" pady="10">
     <img src="UI/zoopedia/biome/reef_zoopedia_biomebrush.dds" sx="0" sy="0" sw="256" sh="85"/>
    </cell>
   </cell>
  </cell>
  <p/>
  <p/>
  <cell width="260"/>
  <cell width="300">
   <cell width="64">
    <img src="ui/zoopedia/fact-icon64.tga" sx="0" sy="0" sw="64" sh="64"/>
   </cell>
   <cell width="176">
    <color r="255" g="255" b="255">
     <font name="arial" size="12" shadowx="2" shadowy="1" shadowa="50">Datos divertidos del Pre-lenguado</font>
    </color>
   </cell>
   <p/>
   <cell width="280" bgimg="ui/zoopedia/factBG.tga" padx="10">
    <p/>
    <cell width="32" pady="10">
     <img src="ui/zoopedia/fact-bullet.tga" sx="0" sy="0" sw="32" sh="32"/>
    </cell>
    <cell width="202" pady="10">
     <color r="255" g="255" b="255">Vivia en el eoceno</color>
    </cell>
	<cell width="32" pady="10">
		<img src="ui/zoopedia/fact-bullet.tga" sx="0" sy="0" sw="32" sh="32"/>
	</cell>    
    <cell width="202" pady="10">
     <color r="255" g="255" b="255">Vivia en Monte Bolca</color>
    </cell>
	<cell width="32" pady="10">
		<img src="ui/zoopedia/fact-bullet.tga" sx="0" sy="0" sw="32" sh="32"/>
	</cell>        
    <cell width="202" pady="10">
     <color r="255" g="255" b="255">Media 6 cm</color> 
    </cell>
  </cell>
  </cell>
  <cell width="340">
   <color r="255" g="248" b="178">
    Para adoptar un pre-lenguado necesitas 2 estrellas de fama en el zoo. 
   </color>
   <p/>Amphistium es un pez que vivio en Monte bolca, en el eoceno. Media 4 cm. Tal y como dice el nombre vulgar, pre-lenguado, es el antepasado de los lenguados. Es la especie transitoria de los peces simetricos a los lenguados, junto con Heteronectes. Este pez tenia un ojo vizco, mas arriba que el del otro lado. El ojo no se le subio por el hecho de que el pez nadaba de lado, ya que es lo que pensaria mucha gente. Este pez ya tenia los ojos torcidos antes de nadar de lado por el fondo. El ojo se movio por mutaciones casuales, igual que le podria haber pasado a cualquier otro pez, pero esta especie se adapto a la mutacion. Amphistium tenia un campo de vision menor, pero de esta manera podia medir mejor las distancias para capturar las presas. La seleccion natural acepto esta mutacion como valida, y el pez pudo seguir evolucoinando hasta tener un ojo en la frente, como Psettodes, y finalmente puede nadar de lado y conseguir los dos ojos en el mismo lado, como Eobothus y el resto de lenguados actuales.
   <p/>
  </cell>
  <p/>
  <cell width="260"/>
  <cell width="620">
   Hecho por: <color r="255" g="231" b="135">Imago</color>
  </cell>
 </text>
</zoopedia_amphistiumpar>
</ZT2Strings>